{
    "tutorials": [
        {
            "id": "01-basics",
            "label": "Введение и основы",
            "description": "Введение и основы языка LOGO. Встреча с черепахой.",
            "steps": 7
        },
        {
            "id": "02-controlling",
            "label": "Controlling the Turtle and Pen",
            "description": "Basic turtle commands, working with graphics",
            "steps": 10
        },
        {
            "id": "03-labels",
            "label": "Cool Labels",
            "description": "Printing nice labels using turtle graphics",
            "steps": 7
        }
    ]
}