{
  "tutorials": [
    {
      "id": "01-basics",
      "label": "Turtle Basics",
      "description": "Introduction and LOGO language basics",
      "level": "Beginner",
      "steps": [
        {
          "name": "Welcome",
          "id": "01-welcome"
        },
        {
          "name": "Basic movement commands",
          "id": "02-movement"
        },
        {
          "name": "Controlling the pen",
          "id": "03-pen"
        },
        {
          "name": "Adding the colors",
          "id": "04-colors"
        },
        {
          "name": "Hiding the turtle",
          "id": "05-hide"
        },
        {
          "name": "Short commands",
          "id": "06-shortcuts"
        },
        {
          "name": "Tutorial is completed",
          "id": "07-finish"
        }
      ]
    },
    {
      "id": "02-graphics",
      "label": "Graphic primitives",
      "description": "Working with various graphic commands",
      "level": "Beginner",
      "steps": [
        {
          "name": "Working with labels",
          "id": "01-label"
        },
        {
          "name": "Circles and segments",
          "id": "02-arc"
        },
        {
          "name": "Putting the pen back down",
          "id": "step-03"
        },
        {
          "name": "Hiding the turtle",
          "id": "step-04"
        },
        {
          "name": "Drawing with the hidden turtle",
          "id": "step-05"
        },
        {
          "name": "The turtle reappears",
          "id": "step-06"
        },
        {
          "name": "The Width of the Pen",
          "id": "step-07"
        },
        {
          "name": "Wider line",
          "id": "step-08"
        },
        {
          "name": "The Color of the Pen",
          "id": "step-09"
        },
        {
          "name": "Cogratulations!",
          "id": "step-10"
        }
      ]
    }
  ]
}
